{"cameraMode":{"drawMode":0,"name":"Shaded","section":"Shading Mode"},"sceneLighting":false,"audioPlay":false,"sceneViewState":{"m_AlwaysRefresh":false,"showFog":true,"showSkybox":false,"showFlares":true,"showImageEffects":true,"showParticleSystems":true,"showVisualEffectGraphs":true,"m_FxEnabled":true},"in2DMode":false,"pivot":{"x":4.238225936889648,"y":0.7795385718345642,"z":0.7837449312210083},"rotation":{"x":0.12411487102508545,"y":0.26078781485557558,"z":-0.033829495310783389,"w":0.956787645816803},"size":0.7926352620124817,"orthographic":false}